MANIFEST.in
README.md
VERSION
setup.cfg
setup.py
bin/dynamodbctl
bin/s3ctl
dynomite/__init__.py
dynomite.egg-info/PKG-INFO
dynomite.egg-info/SOURCES.txt
dynomite.egg-info/dependency_links.txt
dynomite.egg-info/requires.txt
dynomite.egg-info/top_level.txt
dynomite/dynamodb/__init__.py
dynomite/dynamodb/templates/backup_pipeline_def.json
dynomite/dynamodb/templates/data_pipeline_default_resource_role.json
dynomite/dynamodb/templates/data_pipeline_default_resource_role_policy.json
dynomite/dynamodb/templates/data_pipeline_default_role.json
dynomite/dynamodb/templates/data_pipeline_default_role_policy.json
dynomite/dynamodb/templates/restore_pipeline_def.json
dynomite/s3/__init__.py
dynomite/templates/bucket_policy.json
dynomite/templates/user_policy.json