Metadata-Version: 1.1
Name: dynomite
Version: 0.4.0
Summary: Dynomite
Home-page: https://github.com/socotra/dynomite
Author: Chris Antenesse
Author-email: chris.antenesse@socotra.com
License: all rights reserved
Download-URL: https://github.com/socotra/dynomite/tarball/0.1.0
Platform: UNKNOWN
